collibra_catalog_external_profiling_upload/__init__.py
collibra_catalog_external_profiling_upload/api_client.py
collibra_catalog_external_profiling_upload/configuration.py
collibra_catalog_external_profiling_upload/rest.py
collibra_catalog_external_profiling_upload/api/__init__.py
collibra_catalog_external_profiling_upload/api/profiling_api.py
collibra_catalog_external_profiling_upload/models/__init__.py
collibra_catalog_external_profiling_upload/models/asset_identifier.py
collibra_catalog_external_profiling_upload/models/categorical_metadata.py
collibra_catalog_external_profiling_upload/models/column_profile.py
collibra_catalog_external_profiling_upload/models/counts.py
collibra_catalog_external_profiling_upload/models/data_profiling_request.py
collibra_catalog_external_profiling_upload/models/data_profiling_response.py
collibra_catalog_external_profiling_upload/models/database_metadata.py
collibra_catalog_external_profiling_upload/models/distributions.py
collibra_catalog_external_profiling_upload/models/histogram_bin.py
collibra_catalog_external_profiling_upload/models/point.py
collibra_catalog_external_profiling_upload/models/quantiles.py
collibra_catalog_external_profiling_upload/models/samples.py
collibra_catalog_external_profiling_upload/models/statistics.py
test/__init__.py
test/test_asset_identifier.py
test/test_categorical_metadata.py
test/test_column_profile.py
test/test_counts.py
test/test_data_profiling_request.py
test/test_data_profiling_response.py
test/test_database_metadata.py
test/test_distributions.py
test/test_histogram_bin.py
test/test_point.py
test/test_profiling_api.py
test/test_quantiles.py
test/test_samples.py
test/test_statistics.py
collibra_catalog_external_profiling_upload_100-1.0.0.dist-info/METADATA
collibra_catalog_external_profiling_upload_100-1.0.0.dist-info/WHEEL
collibra_catalog_external_profiling_upload_100-1.0.0.dist-info/top_level.txt
collibra_catalog_external_profiling_upload_100-1.0.0.dist-info/RECORD
